[{"l": [[0, 9, 2], [0, 10, 2], [0, 15, 2], [0, 21, 2], [0, 28, 2]], "l.": [[0, 9, 4], [0, 10, 4], [0, 15, 4], [0, 21, 4], [0, 28, 4]], "li": [[0, 9, 4], [0, 29, 4], [0, 30, 4], [1, 6, 4], [1, 16, 4]], "l.i": [[0, 9, 6], [0, 29, 6], [0, 30, 6], [1, 6, 6], [1, 16, 6]], "li.": [[0, 9, 6], [0, 29, 6], [0, 30, 6], [1, 6, 6], [1, 16, 6]], "lik": [[0, 9, 6], [1, 6, 6], [1, 16, 6], [0, 9, 6]], "l.k": [[0, 9, 6], [1, 6, 6], [1, 16, 6], [0, 9, 6]], "lk": [[0, 9, 4], [1, 6, 4], [1, 16, 4], [0, 9, 4]], "l.ik": [[0, 9, 8], [1, 6, 8], [1, 16, 8], [0, 9, 8]], "li.k": [[0, 9, 8], [1, 6, 8], [1, 16, 8], [0, 9, 8]], "lik.": [[0, 9, 8], [1, 6, 8], [1, 16, 8], [0, 9, 8]], "like": [[0, 9, 8], [1, 6, 8], [1, 16, 8], [0, 9, 8]], "l.ke": [[0, 9, 8], [1, 6, 8], [1, 16, 8], [0, 9, 8]], "lke": [[0, 9, 6], [1, 6, 6], [1, 16, 6], [0, 9, 6]], "l.ike": [[0, 9, 10], [1, 6, 10], [1, 16, 10], [0, 9, 10]], "li.e": [[0, 9, 8], [1, 6, 8], [1, 16, 8], [0, 9, 8]], "lie": [[0, 9, 6], [1, 6, 6], [1, 16, 6], [0, 9, 6]], "li.ke": [[0, 9, 10], [1, 6, 10], [1, 16, 10], [0, 9, 10]], "lik.e": [[0, 9, 10], [1, 6, 10], [1, 16, 10], [0, 9, 10]], "like.": [[0, 9, 10], [1, 6, 10], [1, 16, 10], [0, 9, 10]], "like ": [[0, 9, 10], [1, 6, 10], [1, 16, 10], [0, 9, 10]], "l.ke ": [[0, 9, 10], [1, 6, 10], [1, 16, 10], [0, 9, 10]], "lke ": [[0, 9, 8], [1, 6, 8], [1, 16, 8], [0, 9, 8]], "l.ike ": [[0, 9, 12], [1, 6, 12], [1, 16, 12], [0, 9, 12]], "li.e ": [[0, 9, 10], [1, 6, 10], [1, 16, 10], [0, 9, 10]], "lie ": [[0, 9, 8], [1, 6, 8], [1, 16, 8], [0, 9, 8]], "li.ke ": [[0, 9, 12], [1, 6, 12], [1, 16, 12], [0, 9, 12]], "lik. ": [[0, 9, 10], [1, 6, 10], [1, 16, 10], [0, 9, 10]], "lik ": [[0, 9, 8], [1, 6, 8], [1, 16, 8], [0, 9, 8]], "lik.e ": [[0, 9, 12], [1, 6, 12], [1, 16, 12], [0, 9, 12]], "like. ": [[0, 9, 12], [1, 6, 12], [1, 16, 12], [0, 9, 12]], "like .": [[0, 9, 12], [1, 6, 12], [1, 16, 12], [0, 9, 12]], "like p": [[0, 9, 12], [0, 9, 12]], "l.ke p": [[0, 9, 12], [0, 9, 12]], "lke p": [[0, 9, 10], [0, 9, 10]], "l.ike p": [[0, 9, 14], [0, 9, 14]], "li.e p": [[0, 9, 12], [0, 9, 12]], "lie p": [[0, 9, 10], [0, 9, 10]], "li.ke p": [[0, 9, 14], [0, 9, 14]], "lik. p": [[0, 9, 12], [0, 9, 12]], "lik p": [[0, 9, 10], [0, 9, 10]], "lik.e p": [[0, 9, 14], [0, 9, 14]], "like.p": [[0, 9, 12], [0, 9, 12]], "likep": [[0, 9, 10], [0, 9, 10]], "like. p": [[0, 9, 14], [0, 9, 14]], "like .p": [[0, 9, 14], [0, 9, 14]], "like p.": [[0, 9, 14], [0, 9, 14]], "like py": [[0, 9, 14], [0, 9, 14]], "l.ke py": [[0, 9, 14], [0, 9, 14]], "lke py": [[0, 9, 12], [0, 9, 12]], "l.ike py": [[0, 9, 16], [0, 9, 16]], "li.e py": [[0, 9, 14], [0, 9, 14]], "lie py": [[0, 9, 12], [0, 9, 12]], "li.ke py": [[0, 9, 16], [0, 9, 16]], "lik. py": [[0, 9, 14], [0, 9, 14]], "lik py": [[0, 9, 12], [0, 9, 12]], "lik.e py": [[0, 9, 16], [0, 9, 16]], "like.py": [[0, 9, 14], [0, 9, 14]], "likepy": [[0, 9, 12], [0, 9, 12]], "like. py": [[0, 9, 16], [0, 9, 16]], "like .y": [[0, 9, 14], [0, 9, 14]], "like y": [[0, 9, 12], [0, 9, 12]], "like .py": [[0, 9, 16], [0, 9, 16]], "like p.y": [[0, 9, 16], [0, 9, 16]], "like py.": [[0, 9, 16], [0, 9, 16]], "like pyt": [[0, 9, 16], [0, 9, 16]], "l.ke pyt": [[0, 9, 16], [0, 9, 16]], "lke pyt": [[0, 9, 14], [0, 9, 14]], "l.ike pyt": [[0, 9, 18], [0, 9, 18]], "li.e pyt": [[0, 9, 16], [0, 9, 16]], "lie pyt": [[0, 9, 14], [0, 9, 14]], "li.ke pyt": [[0, 9, 18], [0, 9, 18]], "lik. pyt": [[0, 9, 16], [0, 9, 16]], "lik pyt": [[0, 9, 14], [0, 9, 14]], "lik.e pyt": [[0, 9, 18], [0, 9, 18]], "like.pyt": [[0, 9, 16], [0, 9, 16]], "likepyt": [[0, 9, 14], [0, 9, 14]], "like. pyt": [[0, 9, 18], [0, 9, 18]], "like .yt": [[0, 9, 16], [0, 9, 16]], "like yt": [[0, 9, 14], [0, 9, 14]], "like .pyt": [[0, 9, 18], [0, 9, 18]], "like p.t": [[0, 9, 16], [0, 9, 16]], "like pt": [[0, 9, 14], [0, 9, 14]], "like p.yt": [[0, 9, 18], [0, 9, 18]], "like py.t": [[0, 9, 18], [0, 9, 18]], "like pyt.": [[0, 9, 18], [0, 9, 18]], "like pyth": [[0, 9, 18], [0, 9, 18]], "l.ke pyth": [[0, 9, 18], [0, 9, 18]], "lke pyth": [[0, 9, 16], [0, 9, 16]], "l.ike pyth": [[0, 9, 20], [0, 9, 20]], "li.e pyth": [[0, 9, 18], [0, 9, 18]], "lie pyth": [[0, 9, 16], [0, 9, 16]], "li.ke pyth": [[0, 9, 20], [0, 9, 20]], "lik. pyth": [[0, 9, 18], [0, 9, 18]], "lik pyth": [[0, 9, 16], [0, 9, 16]], "lik.e pyth": [[0, 9, 20], [0, 9, 20]], "like.pyth": [[0, 9, 18], [0, 9, 18]], "likepyth": [[0, 9, 16], [0, 9, 16]], "like. pyth": [[0, 9, 20], [0, 9, 20]], "like .yth": [[0, 9, 18], [0, 9, 18]], "like yth": [[0, 9, 16], [0, 9, 16]], "like .pyth": [[0, 9, 20], [0, 9, 20]], "like p.th": [[0, 9, 18], [0, 9, 18]], "like pth": [[0, 9, 16], [0, 9, 16]], "like p.yth": [[0, 9, 20], [0, 9, 20]], "like py.h": [[0, 9, 18], [0, 9, 18]], "like pyh": [[0, 9, 16], [0, 9, 16]], "like py.th": [[0, 9, 20], [0, 9, 20]], "like pyt.h": [[0, 9, 20], [0, 9, 20]], "like pyth.": [[0, 9, 20], [0, 9, 20]], "lo": [[0, 10, 4], [0, 10, 4]], "l.o": [[0, 10, 6], [0, 10, 6]], "lo.": [[0, 10, 6]], "loo": [[0, 10, 6]], "l.oo": [[0, 10, 8]], "lo.o": [[0, 10, 8]], "loo.": [[0, 10, 8]], "look": [[0, 10, 8]], "l.ok": [[0, 10, 8]], "lok": [[0, 10, 6], [0, 10, 6]], "l.ook": [[0, 10, 10]], "lo.k": [[0, 10, 8]], "lo.ok": [[0, 10, 10]], "loo.k": [[0, 10, 10]], "look.": [[0, 10, 10]], "look ": [[0, 10, 10]], "l.ok ": [[0, 10, 10]], "lok ": [[0, 10, 8], [0, 10, 8]], "l.ook ": [[0, 10, 12]], "lo.k ": [[0, 10, 10]], "lo.ok ": [[0, 10, 12]], "loo. ": [[0, 10, 10]], "loo ": [[0, 10, 8]], "loo.k ": [[0, 10, 12]], "look. ": [[0, 10, 12]], "look .": [[0, 10, 12]], "look a": [[0, 10, 12]], "l.ok a": [[0, 10, 12]], "lok a": [[0, 10, 10], [0, 10, 10]], "l.ook a": [[0, 10, 14]], "lo.k a": [[0, 10, 12]], "lo.ok a": [[0, 10, 14]], "loo. a": [[0, 10, 12]], "loo a": [[0, 10, 10]], "loo.k a": [[0, 10, 14]], "look.a": [[0, 10, 12]], "looka": [[0, 10, 10]], "look. a": [[0, 10, 14]], "look .a": [[0, 10, 14]], "look a.": [[0, 10, 14]], "look at": [[0, 10, 14]], "l.ok at": [[0, 10, 14]], "lok at": [[0, 10, 12], [0, 10, 12]], "l.ook at": [[0, 10, 16]], "lo.k at": [[0, 10, 14]], "lo.ok at": [[0, 10, 16]], "loo. at": [[0, 10, 14]], "loo at": [[0, 10, 12]], "loo.k at": [[0, 10, 16]], "look.at": [[0, 10, 14]], "lookat": [[0, 10, 12]], "look. at": [[0, 10, 16]], "look .t": [[0, 10, 14]], "look t": [[0, 10, 12]], "look .at": [[0, 10, 16]], "look a.t": [[0, 10, 16]], "look at.": [[0, 10, 16]], "look at ": [[0, 10, 16]], "l.ok at ": [[0, 10, 16]], "lok at ": [[0, 10, 14], [0, 10, 14]], "l.ook at ": [[0, 10, 18]], "lo.k at ": [[0, 10, 16]], "lo.ok at ": [[0, 10, 18]], "loo. at ": [[0, 10, 16]], "loo at ": [[0, 10, 14]], "loo.k at ": [[0, 10, 18]], "look.at ": [[0, 10, 16]], "lookat ": [[0, 10, 14]], "look. at ": [[0, 10, 18]], "look .t ": [[0, 10, 16]], "look t ": [[0, 10, 14]], "look .at ": [[0, 10, 18]], "look a. ": [[0, 10, 16]], "look a ": [[0, 10, 14]], "look a.t ": [[0, 10, 18]], "look at. ": [[0, 10, 18]], "look at .": [[0, 10, 18]], "look at t": [[0, 10, 18]], "l.ok at t": [[0, 10, 18]], "lok at t": [[0, 10, 16], [0, 10, 16]], "l.ook at t": [[0, 10, 20]], "lo.k at t": [[0, 10, 18]], "lo.ok at t": [[0, 10, 20]], "loo. at t": [[0, 10, 18]], "loo at t": [[0, 10, 16]], "loo.k at t": [[0, 10, 20]], "look.at t": [[0, 10, 18]], "lookat t": [[0, 10, 16]], "look. at t": [[0, 10, 20]], "look .t t": [[0, 10, 18]], "look t t": [[0, 10, 16]], "look .at t": [[0, 10, 20]], "look a. t": [[0, 10, 18]], "look a t": [[0, 10, 16]], "look a.t t": [[0, 10, 20]], "look at.t": [[0, 10, 18]], "look att": [[0, 10, 16]], "look at. t": [[0, 10, 20]], "look at .t": [[0, 10, 20]], "look at t.": [[0, 10, 20]], "l ": [[0, 15, 4]], "l. ": [[0, 15, 6]], "l .": [[0, 15, 6]], "l d": [[0, 15, 6]], "l.d": [[0, 15, 6]], "ld": [[0, 15, 4]], "l. d": [[0, 15, 8]], "l .d": [[0, 15, 8]], "l d.": [[0, 15, 8]], "l dr": [[0, 15, 8]], "l.dr": [[0, 15, 8]], "ldr": [[0, 15, 6]], "l. dr": [[0, 15, 10]], "l .r": [[0, 15, 8]], "l r": [[0, 15, 6]], "l .dr": [[0, 15, 10]], "l d.r": [[0, 15, 10]], "l dr.": [[0, 15, 10]], "l dra": [[0, 15, 10]], "l.dra": [[0, 15, 10]], "ldra": [[0, 15, 8]], "l. dra": [[0, 15, 12]], "l .ra": [[0, 15, 10]], "l ra": [[0, 15, 8]], "l .dra": [[0, 15, 12]], "l d.a": [[0, 15, 10]], "l da": [[0, 15, 8]], "l d.ra": [[0, 15, 12]], "l dr.a": [[0, 15, 12]], "l dra.": [[0, 15, 12]], "l drak": [[0, 15, 12]], "l.drak": [[0, 15, 12]], "ldrak": [[0, 15, 10]], "l. drak": [[0, 15, 14]], "l .rak": [[0, 15, 12]], "l rak": [[0, 15, 10]], "l .drak": [[0, 15, 14]], "l d.ak": [[0, 15, 12]], "l dak": [[0, 15, 10]], "l d.rak": [[0, 15, 14]], "l dr.k": [[0, 15, 12]], "l drk": [[0, 15, 10]], "l dr.ak": [[0, 15, 14]], "l dra.k": [[0, 15, 14]], "l drak.": [[0, 15, 14]], "l drake": [[0, 15, 14]], "l.drake": [[0, 15, 14]], "ldrake": [[0, 15, 12]], "l. drake": [[0, 15, 16]], "l .rake": [[0, 15, 14]], "l rake": [[0, 15, 12]], "l .drake": [[0, 15, 16]], "l d.ake": [[0, 15, 14]], "l dake": [[0, 15, 12]], "l d.rake": [[0, 15, 16]], "l dr.ke": [[0, 15, 14]], "l drke": [[0, 15, 12]], "l dr.ake": [[0, 15, 16]], "l dra.e": [[0, 15, 14]], "l drae": [[0, 15, 12]], "l dra.ke": [[0, 15, 16]], "l drak.e": [[0, 15, 16]], "l drake.": [[0, 15, 16]], "l drake ": [[0, 15, 16]], "l.drake ": [[0, 15, 16]], "ldrake ": [[0, 15, 14]], "l. drake ": [[0, 15, 18]], "l .rake ": [[0, 15, 16]], "l rake ": [[0, 15, 14]], "l .drake ": [[0, 15, 18]], "l d.ake ": [[0, 15, 16]], "l dake ": [[0, 15, 14]], "l d.rake ": [[0, 15, 18]], "l dr.ke ": [[0, 15, 16]], "l drke ": [[0, 15, 14]], "l dr.ake ": [[0, 15, 18]], "l dra.e ": [[0, 15, 16]], "l drae ": [[0, 15, 14]], "l dra.ke ": [[0, 15, 18]], "l drak. ": [[0, 15, 16]], "l drak ": [[0, 15, 14]], "l drak.e ": [[0, 15, 18]], "l drake. ": [[0, 15, 18]], "l drake .": [[0, 15, 18]], "l drake j": [[0, 15, 18]], "l.drake j": [[0, 15, 18]], "ldrake j": [[0, 15, 16]], "l. drake j": [[0, 15, 20]], "l .rake j": [[0, 15, 18]], "l rake j": [[0, 15, 16]], "l .drake j": [[0, 15, 20]], "l d.ake j": [[0, 15, 18]], "l dake j": [[0, 15, 16]], "l d.rake j": [[0, 15, 20]], "l dr.ke j": [[0, 15, 18]], "l drke j": [[0, 15, 16]], "l dr.ake j": [[0, 15, 20]], "l dra.e j": [[0, 15, 18]], "l drae j": [[0, 15, 16]], "l dra.ke j": [[0, 15, 20]], "l drak. j": [[0, 15, 18]], "l drak j": [[0, 15, 16]], "l drak.e j": [[0, 15, 20]], "l drake.j": [[0, 15, 18]], "l drakej": [[0, 15, 16]], "l drake. j": [[0, 15, 20]], "l drake .j": [[0, 15, 20]], "l drake j.": [[0, 15, 20]], "lu": [[0, 21, 4]], "l.u": [[0, 21, 6]], "lu.": [[0, 21, 6]], "lun": [[0, 21, 6]], "l.n": [[0, 21, 6], [0, 28, 6], [1, 4, 6]], "ln": [[0, 21, 4], [0, 28, 4], [1, 4, 4]], "l.un": [[0, 21, 8]], "lu.n": [[0, 21, 8]], "lun.": [[0, 21, 8]], "lund": [[0, 21, 8]], "l.nd": [[0, 21, 8]], "lnd": [[0, 21, 6]], "l.und": [[0, 21, 10]], "lu.d": [[0, 21, 8]], "lud": [[0, 21, 6]], "lu.nd": [[0, 21, 10]], "lun.d": [[0, 21, 10]], "lund.": [[0, 21, 10]], "lundh": [[0, 21, 10]], "l.ndh": [[0, 21, 10]], "lndh": [[0, 21, 8]], "l.undh": [[0, 21, 12]], "lu.dh": [[0, 21, 10]], "ludh": [[0, 21, 8]], "lu.ndh": [[0, 21, 12]], "lun.h": [[0, 21, 10]], "lunh": [[0, 21, 8]], "lun.dh": [[0, 21, 12]], "lund.h": [[0, 21, 12]], "lundh.": [[0, 21, 12]], "lundh ": [[0, 21, 12]], "l.ndh ": [[0, 21, 12]], "lndh ": [[0, 21, 10]], "l.undh ": [[0, 21, 14]], "lu.dh ": [[0, 21, 12]], "ludh ": [[0, 21, 10]], "lu.ndh ": [[0, 21, 14]], "lun.h ": [[0, 21, 12]], "lunh ": [[0, 21, 10]], "lun.dh ": [[0, 21, 14]], "lund. ": [[0, 21, 12]], "lund ": [[0, 21, 10]], "lund.h ": [[0, 21, 14]], "lundh. ": [[0, 21, 14]], "lundh .": [[0, 21, 14]], "lundh f": [[0, 21, 14]], "l.ndh f": [[0, 21, 14]], "lndh f": [[0, 21, 12]], "l.undh f": [[0, 21, 16]], "lu.dh f": [[0, 21, 14]], "ludh f": [[0, 21, 12]], "lu.ndh f": [[0, 21, 16]], "lun.h f": [[0, 21, 14]], "lunh f": [[0, 21, 12]], "lun.dh f": [[0, 21, 16]], "lund. f": [[0, 21, 14]], "lund f": [[0, 21, 12]], "lund.h f": [[0, 21, 16]], "lundh.f": [[0, 21, 14]], "lundhf": [[0, 21, 12]], "lundh. f": [[0, 21, 16]], "lundh .f": [[0, 21, 16]], "lundh f.": [[0, 21, 16]], "lundh fo": [[0, 21, 16]], "l.ndh fo": [[0, 21, 16]], "lndh fo": [[0, 21, 14]], "l.undh fo": [[0, 21, 18]], "lu.dh fo": [[0, 21, 16]], "ludh fo": [[0, 21, 14]], "lu.ndh fo": [[0, 21, 18]], "lun.h fo": [[0, 21, 16]], "lunh fo": [[0, 21, 14]], "lun.dh fo": [[0, 21, 18]], "lund. fo": [[0, 21, 16]], "lund fo": [[0, 21, 14]], "lund.h fo": [[0, 21, 18]], "lundh.fo": [[0, 21, 16]], "lundhfo": [[0, 21, 14]], "lundh. fo": [[0, 21, 18]], "lundh .o": [[0, 21, 16]], "lundh o": [[0, 21, 14]], "lundh .fo": [[0, 21, 18]], "lundh f.o": [[0, 21, 18]], "lundh fo.": [[0, 21, 18]], "lundh for": [[0, 21, 18]], "l.ndh for": [[0, 21, 18]], "lndh for": [[0, 21, 16]], "l.undh for": [[0, 21, 20]], "lu.dh for": [[0, 21, 18]], "ludh for": [[0, 21, 16]], "lu.ndh for": [[0, 21, 20]], "lun.h for": [[0, 21, 18]], "lunh for": [[0, 21, 16]], "lun.dh for": [[0, 21, 20]], "lund. for": [[0, 21, 18]], "lund for": [[0, 21, 16]], "lund.h for": [[0, 21, 20]], "lundh.for": [[0, 21, 18]], "lundhfor": [[0, 21, 16]], "lundh. for": [[0, 21, 20]], "lundh .or": [[0, 21, 18]], "lundh or": [[0, 21, 16]], "lundh .for": [[0, 21, 20]], "lundh f.r": [[0, 21, 18]], "lundh fr": [[0, 21, 16]], "lundh f.or": [[0, 21, 20]], "lundh fo.r": [[0, 21, 20]], "lundh for.": [[0, 21, 20]], "la": [[0, 28, 4], [1, 4, 4], [1, 10, 4], [1, 50, 4]], "l.a": [[0, 28, 6], [1, 4, 6], [1, 10, 6], [1, 50, 6]], "la.": [[0, 28, 6], [1, 4, 6]], "lan": [[0, 28, 6], [1, 4, 6]], "l.an": [[0, 28, 8], [1, 4, 8]], "la.n": [[0, 28, 8], [1, 4, 8]], "lan.": [[0, 28, 8], [1, 4, 8]], "lang": [[0, 28, 8], [1, 4, 8]], "l.ng": [[0, 28, 8], [1, 4, 8]], "lng": [[0, 28, 6], [1, 4, 6]], "l.ang": [[0, 28, 10], [1, 4, 10]], "la.g": [[0, 28, 8], [1, 4, 8]], "lag": [[0, 28, 6], [1, 4, 6]], "la.ng": [[0, 28, 10], [1, 4, 10]], "lan.g": [[0, 28, 10], [1, 4, 10]], "lang.": [[0, 28, 10], [1, 4, 10]], "langu": [[0, 28, 10], [1, 4, 10]], "l.ngu": [[0, 28, 10], [1, 4, 10]], "lngu": [[0, 28, 8], [1, 4, 8]], "l.angu": [[0, 28, 12], [1, 4, 12]], "la.gu": [[0, 28, 10], [1, 4, 10]], "lagu": [[0, 28, 8], [1, 4, 8]], "la.ngu": [[0, 28, 12], [1, 4, 12]], "lan.u": [[0, 28, 10], [1, 4, 10]], "lanu": [[0, 28, 8], [1, 4, 8]], "lan.gu": [[0, 28, 12], [1, 4, 12]], "lang.u": [[0, 28, 12], [1, 4, 12]], "langu.": [[0, 28, 12], [1, 4, 12]], "langua": [[0, 28, 12], [1, 4, 12]], "l.ngua": [[0, 28, 12], [1, 4, 12]], "lngua": [[0, 28, 10], [1, 4, 10]], "l.angua": [[0, 28, 14], [1, 4, 14]], "la.gua": [[0, 28, 12], [1, 4, 12]], "lagua": [[0, 28, 10], [1, 4, 10]], "la.ngua": [[0, 28, 14], [1, 4, 14]], "lan.ua": [[0, 28, 12], [1, 4, 12]], "lanua": [[0, 28, 10], [1, 4, 10]], "lan.gua": [[0, 28, 14], [1, 4, 14]], "lang.a": [[0, 28, 12], [1, 4, 12]], "langa": [[0, 28, 10], [1, 4, 10]], "lang.ua": [[0, 28, 14], [1, 4, 14]], "langu.a": [[0, 28, 14], [1, 4, 14]], "langua.": [[0, 28, 14], [1, 4, 14]], "languag": [[0, 28, 14], [1, 4, 14]], "l.nguag": [[0, 28, 14], [1, 4, 14]], "lnguag": [[0, 28, 12], [1, 4, 12]], "l.anguag": [[0, 28, 16], [1, 4, 16]], "la.guag": [[0, 28, 14], [1, 4, 14]], "laguag": [[0, 28, 12], [1, 4, 12]], "la.nguag": [[0, 28, 16], [1, 4, 16]], "lan.uag": [[0, 28, 14], [1, 4, 14]], "lanuag": [[0, 28, 12], [1, 4, 12]], "lan.guag": [[0, 28, 16], [1, 4, 16]], "lang.ag": [[0, 28, 14], [1, 4, 14]], "langag": [[0, 28, 12], [1, 4, 12]], "lang.uag": [[0, 28, 16], [1, 4, 16]], "langu.g": [[0, 28, 14], [1, 4, 14]], "langug": [[0, 28, 12], [1, 4, 12]], "langu.ag": [[0, 28, 16], [1, 4, 16]], "langua.g": [[0, 28, 16], [1, 4, 16]], "languag.": [[0, 28, 16], [1, 4, 16]], "language": [[0, 28, 16], [1, 4, 16]], "l.nguage": [[0, 28, 16], [1, 4, 16]], "lnguage": [[0, 28, 14], [1, 4, 14]], "l.anguage": [[0, 28, 18], [1, 4, 18]], "la.guage": [[0, 28, 16], [1, 4, 16]], "laguage": [[0, 28, 14], [1, 4, 14]], "la.nguage": [[0, 28, 18], [1, 4, 18]], "lan.uage": [[0, 28, 16], [1, 4, 16]], "lanuage": [[0, 28, 14], [1, 4, 14]], "lan.guage": [[0, 28, 18], [1, 4, 18]], "lang.age": [[0, 28, 16], [1, 4, 16]], "langage": [[0, 28, 14], [1, 4, 14]], "lang.uage": [[0, 28, 18], [1, 4, 18]], "langu.ge": [[0, 28, 16], [1, 4, 16]], "languge": [[0, 28, 14], [1, 4, 14]], "langu.age": [[0, 28, 18], [1, 4, 18]], "langua.e": [[0, 28, 16], [1, 4, 16]], "languae": [[0, 28, 14], [1, 4, 14]], "langua.ge": [[0, 28, 18], [1, 4, 18]], "languag.e": [[0, 28, 18], [1, 4, 18]], "language.": [[0, 28, 18], [1, 4, 18]], "language ": [[0, 28, 18], [1, 4, 18]], "l.nguage ": [[0, 28, 18], [1, 4, 18]], "lnguage ": [[0, 28, 16], [1, 4, 16]], "l.anguage ": [[0, 28, 20], [1, 4, 20]], "la.guage ": [[0, 28, 18], [1, 4, 18]], "laguage ": [[0, 28, 16], [1, 4, 16]], "la.nguage ": [[0, 28, 20], [1, 4, 20]], "lan.uage ": [[0, 28, 18], [1, 4, 18]], "lanuage ": [[0, 28, 16], [1, 4, 16]], "lan.guage ": [[0, 28, 20], [1, 4, 20]], "lang.age ": [[0, 28, 18], [1, 4, 18]], "langage ": [[0, 28, 16], [1, 4, 16]], "lang.uage ": [[0, 28, 20], [1, 4, 20]], "langu.ge ": [[0, 28, 18], [1, 4, 18]], "languge ": [[0, 28, 16], [1, 4, 16]], "langu.age ": [[0, 28, 20], [1, 4, 20]], "langua.e ": [[0, 28, 18], [1, 4, 18]], "languae ": [[0, 28, 16], [1, 4, 16]], "langua.ge ": [[0, 28, 20], [1, 4, 20]], "languag. ": [[0, 28, 18], [1, 4, 18]], "languag ": [[0, 28, 16], [1, 4, 16]], "languag.e ": [[0, 28, 20], [1, 4, 20]], "language. ": [[0, 28, 20], [1, 4, 20]], "language .": [[0, 28, 20], [1, 4, 20]], "lib": [[0, 29, 6]], "l.b": [[0, 29, 6]], "lb": [[0, 29, 4]], "l.ib": [[0, 29, 8]], "li.b": [[0, 29, 8]], "lib.": [[0, 29, 8]], "libr": [[0, 29, 8]], "l.br": [[0, 29, 8]], "lbr": [[0, 29, 6]], "l.ibr": [[0, 29, 10]], "li.r": [[0, 29, 8]], "lir": [[0, 29, 6]], "li.br": [[0, 29, 10]], "lib.r": [[0, 29, 10]], "libr.": [[0, 29, 10]], "libra": [[0, 29, 10]], "l.bra": [[0, 29, 10]], "lbra": [[0, 29, 8]], "l.ibra": [[0, 29, 12]], "li.ra": [[0, 29, 10]], "lira": [[0, 29, 8]], "li.bra": [[0, 29, 12]], "lib.a": [[0, 29, 10]], "liba": [[0, 29, 8]], "lib.ra": [[0, 29, 12]], "libr.a": [[0, 29, 12]], "libra.": [[0, 29, 12]], "librar": [[0, 29, 12]], "l.brar": [[0, 29, 12]], "lbrar": [[0, 29, 10]], "l.ibrar": [[0, 29, 14]], "li.rar": [[0, 29, 12]], "lirar": [[0, 29, 10]], "li.brar": [[0, 29, 14]], "lib.ar": [[0, 29, 12]], "libar": [[0, 29, 10]], "lib.rar": [[0, 29, 14]], "libr.r": [[0, 29, 12]], "librr": [[0, 29, 10]], "libr.ar": [[0, 29, 14]], "libra.r": [[0, 29, 14]], "librar.": [[0, 29, 14]], "library": [[0, 29, 14]], "l.brary": [[0, 29, 14]], "lbrary": [[0, 29, 12]], "l.ibrary": [[0, 29, 16]], "li.rary": [[0, 29, 14]], "lirary": [[0, 29, 12]], "li.brary": [[0, 29, 16]], "lib.ary": [[0, 29, 14]], "libary": [[0, 29, 12]], "lib.rary": [[0, 29, 16]], "libr.ry": [[0, 29, 14]], "librry": [[0, 29, 12]], "libr.ary": [[0, 29, 16]], "libra.y": [[0, 29, 14]], "libray": [[0, 29, 12]], "libra.ry": [[0, 29, 16]], "librar.y": [[0, 29, 16]], "library.": [[0, 29, 16]], "library ": [[0, 29, 16]], "l.brary ": [[0, 29, 16]], "lbrary ": [[0, 29, 14]], "l.ibrary ": [[0, 29, 18]], "li.rary ": [[0, 29, 16]], "lirary ": [[0, 29, 14]], "li.brary ": [[0, 29, 18]], "lib.ary ": [[0, 29, 16]], "libary ": [[0, 29, 14]], "lib.rary ": [[0, 29, 18]], "libr.ry ": [[0, 29, 16]], "librry ": [[0, 29, 14]], "libr.ary ": [[0, 29, 18]], "libra.y ": [[0, 29, 16]], "libray ": [[0, 29, 14]], "libra.ry ": [[0, 29, 18]], "librar. ": [[0, 29, 16]], "librar ": [[0, 29, 14]], "librar.y ": [[0, 29, 18]], "library. ": [[0, 29, 18]], "library .": [[0, 29, 18]], "library a": [[0, 29, 18]], "l.brary a": [[0, 29, 18]], "lbrary a": [[0, 29, 16]], "l.ibrary a": [[0, 29, 20]], "li.rary a": [[0, 29, 18]], "lirary a": [[0, 29, 16]], "li.brary a": [[0, 29, 20]], "lib.ary a": [[0, 29, 18]], "libary a": [[0, 29, 16]], "lib.rary a": [[0, 29, 20]], "libr.ry a": [[0, 29, 18]], "librry a": [[0, 29, 16]], "libr.ary a": [[0, 29, 20]], "libra.y a": [[0, 29, 18]], "libray a": [[0, 29, 16]], "libra.ry a": [[0, 29, 20]], "librar. a": [[0, 29, 18]], "librar a": [[0, 29, 16]], "librar.y a": [[0, 29, 20]], "library.a": [[0, 29, 18]], "librarya": [[0, 29, 16]], "library. a": [[0, 29, 20]], "library .a": [[0, 29, 20]], "library a.": [[0, 29, 20]], "lis": [[0, 30, 6], [1, 22, 6], [1, 22, 6], [1, 28, 6]], "l.s": [[0, 30, 6], [1, 9, 6], [1, 22, 6], [1, 22, 6], [1, 28, 6]], "ls": [[0, 30, 4], [1, 9, 4], [1, 22, 4], [1, 22, 4], [1, 28, 4]], "l.is": [[0, 30, 8], [1, 22, 8], [1, 22, 8], [1, 28, 8]], "li.s": [[0, 30, 8], [1, 22, 8], [1, 22, 8], [1, 28, 8]], "lis.": [[0, 30, 8], [1, 22, 8], [1, 22, 8], [1, 28, 8]], "list": [[0, 30, 8], [1, 22, 8], [1, 22, 8], [1, 28, 8]], "l.st": [[0, 30, 8], [1, 22, 8], [1, 22, 8], [1, 28, 8]], "lst": [[0, 30, 6], [1, 22, 6], [1, 22, 6], [1, 28, 6]], "l.ist": [[0, 30, 10], [1, 22, 10], [1, 22, 10], [1, 28, 10]], "li.t": [[0, 30, 8], [1, 22, 8], [1, 22, 8], [1, 28, 8]], "lit": [[0, 30, 6], [1, 22, 6], [1, 22, 6], [1, 28, 6]], "li.st": [[0, 30, 10], [1, 22, 10], [1, 22, 10], [1, 28, 10]], "lis.t": [[0, 30, 10], [1, 22, 10], [1, 22, 10], [1, 28, 10]], "list.": [[0, 30, 10], [1, 22, 10], [1, 22, 10], [1, 28, 10]], "list ": [[0, 30, 10], [1, 22, 10], [1, 28, 10]], "l.st ": [[0, 30, 10], [1, 22, 10], [1, 28, 10]], "lst ": [[0, 30, 8], [1, 22, 8], [1, 28, 8]], "l.ist ": [[0, 30, 12], [1, 22, 12], [1, 28, 12]], "li.t ": [[0, 30, 10], [1, 22, 10], [1, 28, 10]], "lit ": [[0, 30, 8], [1, 22, 8], [1, 28, 8]], "li.st ": [[0, 30, 12], [1, 22, 12], [1, 28, 12]], "lis. ": [[0, 30, 10], [1, 22, 10], [1, 28, 10]], "lis ": [[0, 30, 8], [1, 22, 8], [1, 28, 8]], "lis.t ": [[0, 30, 12], [1, 22, 12], [1, 28, 12]], "list. ": [[0, 30, 12], [1, 22, 12], [1, 28, 12]], "list .": [[0, 30, 12], [1, 22, 12], [1, 28, 12]], "list o": [[0, 30, 12], [1, 28, 12]], "l.st o": [[0, 30, 12], [1, 28, 12]], "lst o": [[0, 30, 10], [1, 28, 10]], "l.ist o": [[0, 30, 14], [1, 28, 14]], "li.t o": [[0, 30, 12], [1, 28, 12]], "lit o": [[0, 30, 10], [1, 28, 10]], "li.st o": [[0, 30, 14], [1, 28, 14]], "lis. o": [[0, 30, 12], [1, 28, 12]], "lis o": [[0, 30, 10], [1, 28, 10]], "lis.t o": [[0, 30, 14], [1, 28, 14]], "list.o": [[0, 30, 12], [1, 28, 12]], "listo": [[0, 30, 10], [1, 28, 10]], "list. o": [[0, 30, 14], [1, 28, 14]], "list .o": [[0, 30, 14], [1, 28, 14]], "list o.": [[0, 30, 14], [1, 28, 14]], "list of": [[0, 30, 14], [1, 28, 14]], "l.st of": [[0, 30, 14], [1, 28, 14]], "lst of": [[0, 30, 12], [1, 28, 12]], "l.ist of": [[0, 30, 16], [1, 28, 16]], "li.t of": [[0, 30, 14], [1, 28, 14]], "lit of": [[0, 30, 12], [1, 28, 12]], "li.st of": [[0, 30, 16], [1, 28, 16]], "lis. of": [[0, 30, 14], [1, 28, 14]], "lis of": [[0, 30, 12], [1, 28, 12]], "lis.t of": [[0, 30, 16], [1, 28, 16]], "list.of": [[0, 30, 14], [1, 28, 14]], "listof": [[0, 30, 12], [1, 28, 12]], "list. of": [[0, 30, 16], [1, 28, 16]], "list .f": [[0, 30, 14], [1, 28, 14]], "list f": [[0, 30, 12], [1, 28, 12]], "list .of": [[0, 30, 16], [1, 28, 16]], "list o.f": [[0, 30, 16], [1, 28, 16]], "list of.": [[0, 30, 16], [1, 28, 16]], "list of ": [[0, 30, 16], [1, 28, 16]], "l.st of ": [[0, 30, 16], [1, 28, 16]], "lst of ": [[0, 30, 14], [1, 28, 14]], "l.ist of ": [[0, 30, 18], [1, 28, 18]], "li.t of ": [[0, 30, 16], [1, 28, 16]], "lit of ": [[0, 30, 14], [1, 28, 14]], "li.st of ": [[0, 30, 18], [1, 28, 18]], "lis. of ": [[0, 30, 16], [1, 28, 16]], "lis of ": [[0, 30, 14], [1, 28, 14]], "lis.t of ": [[0, 30, 18], [1, 28, 18]], "list.of ": [[0, 30, 16], [1, 28, 16]], "listof ": [[0, 30, 14], [1, 28, 14]], "list. of ": [[0, 30, 18], [1, 28, 18]], "list .f ": [[0, 30, 16], [1, 28, 16]], "list f ": [[0, 30, 14], [1, 28, 14]], "list .of ": [[0, 30, 18], [1, 28, 18]], "list o. ": [[0, 30, 16], [1, 28, 16]], "list o ": [[0, 30, 14], [1, 28, 14]], "list o.f ": [[0, 30, 18], [1, 28, 18]], "list of. ": [[0, 30, 18], [1, 28, 18]], "list of .": [[0, 30, 18], [1, 28, 18]], "list of c": [[0, 30, 18]], "l.st of c": [[0, 30, 18]], "lst of c": [[0, 30, 16]], "l.ist of c": [[0, 30, 20]], "li.t of c": [[0, 30, 18]], "lit of c": [[0, 30, 16]], "li.st of c": [[0, 30, 20]], "lis. of c": [[0, 30, 18]], "lis of c": [[0, 30, 16]], "lis.t of c": [[0, 30, 20]], "list.of c": [[0, 30, 18]], "listof c": [[0, 30, 16]], "list. of c": [[0, 30, 20]], "list .f c": [[0, 30, 18]], "list f c": [[0, 30, 16]], "list .of c": [[0, 30, 20]], "list o. c": [[0, 30, 18]], "list o c": [[0, 30, 16]], "list o.f c": [[0, 30, 20]], "list of.c": [[0, 30, 18]], "list ofc": [[0, 30, 16]], "list of. c": [[0, 30, 20]], "list of .c": [[0, 30, 20]], "list of c.": [[0, 30, 20]], "like t": [[1, 6, 12], [1, 16, 12]], "l.ke t": [[1, 6, 12], [1, 16, 12]], "lke t": [[1, 6, 10], [1, 16, 10]], "l.ike t": [[1, 6, 14], [1, 16, 14]], "li.e t": [[1, 6, 12], [1, 16, 12]], "lie t": [[1, 6, 10], [1, 16, 10]], "li.ke t": [[1, 6, 14], [1, 16, 14]], "lik. t": [[1, 6, 12], [1, 16, 12]], "lik t": [[1, 6, 10], [1, 16, 10]], "lik.e t": [[1, 6, 14], [1, 16, 14]], "like.t": [[1, 6, 12], [1, 16, 12]], "liket": [[1, 6, 10], [1, 16, 10]], "like. t": [[1, 6, 14], [1, 16, 14]], "like .t": [[1, 6, 14], [1, 16, 14]], "like t.": [[1, 6, 14], [1, 16, 14]], "like to": [[1, 6, 14], [1, 16, 14]], "l.ke to": [[1, 6, 14], [1, 16, 14]], "lke to": [[1, 6, 12], [1, 16, 12]], "l.ike to": [[1, 6, 16], [1, 16, 16]], "li.e to": [[1, 6, 14], [1, 16, 14]], "lie to": [[1, 6, 12], [1, 16, 12]], "li.ke to": [[1, 6, 16], [1, 16, 16]], "lik. to": [[1, 6, 14], [1, 16, 14]], "lik to": [[1, 6, 12], [1, 16, 12]], "lik.e to": [[1, 6, 16], [1, 16, 16]], "like.to": [[1, 6, 14], [1, 16, 14]], "liketo": [[1, 6, 12], [1, 16, 12]], "like. to": [[1, 6, 16], [1, 16, 16]], "like .o": [[1, 6, 14], [1, 16, 14]], "like o": [[1, 6, 12], [1, 16, 12]], "like .to": [[1, 6, 16], [1, 16, 16]], "like t.o": [[1, 6, 16], [1, 16, 16]], "like to.": [[1, 6, 16], [1, 16, 16]], "like to ": [[1, 6, 16], [1, 16, 16]], "l.ke to ": [[1, 6, 16], [1, 16, 16]], "lke to ": [[1, 6, 14], [1, 16, 14]], "l.ike to ": [[1, 6, 18], [1, 16, 18]], "li.e to ": [[1, 6, 16], [1, 16, 16]], "lie to ": [[1, 6, 14], [1, 16, 14]], "li.ke to ": [[1, 6, 18], [1, 16, 18]], "lik. to ": [[1, 6, 16], [1, 16, 16]], "lik to ": [[1, 6, 14], [1, 16, 14]], "lik.e to ": [[1, 6, 18], [1, 16, 18]], "like.to ": [[1, 6, 16], [1, 16, 16]], "liketo ": [[1, 6, 14], [1, 16, 14]], "like. to ": [[1, 6, 18], [1, 16, 18]], "like .o ": [[1, 6, 16], [1, 16, 16]], "like o ": [[1, 6, 14], [1, 16, 14]], "like .to ": [[1, 6, 18], [1, 16, 18]], "like t. ": [[1, 6, 16], [1, 16, 16]], "like t ": [[1, 6, 14], [1, 16, 14]], "like t.o ": [[1, 6, 18], [1, 16, 18]], "like to. ": [[1, 6, 18], [1, 16, 18]], "like to .": [[1, 6, 18], [1, 16, 18]], "like to k": [[1, 6, 18]], "l.ke to k": [[1, 6, 18]], "lke to k": [[1, 6, 16]], "l.ike to k": [[1, 6, 20]], "li.e to k": [[1, 6, 18]], "lie to k": [[1, 6, 16]], "li.ke to k": [[1, 6, 20]], "lik. to k": [[1, 6, 18]], "lik to k": [[1, 6, 16]], "lik.e to k": [[1, 6, 20]], "like.to k": [[1, 6, 18]], "liketo k": [[1, 6, 16]], "like. to k": [[1, 6, 20]], "like .o k": [[1, 6, 18]], "like o k": [[1, 6, 16]], "like .to k": [[1, 6, 20]], "like t. k": [[1, 6, 18]], "like t k": [[1, 6, 16]], "like t.o k": [[1, 6, 20]], "like to.k": [[1, 6, 18]], "like tok": [[1, 6, 16]], "like to. k": [[1, 6, 20]], "like to .k": [[1, 6, 20]], "like to k.": [[1, 6, 20]], "le": [[1, 9, 4], [1, 10, 4], [1, 50, 4]], "l.e": [[1, 9, 6], [1, 10, 6], [1, 50, 6]], "le.": [[1, 9, 6], [1, 10, 6], [1, 50, 6]], "les": [[1, 9, 6], [1, 9, 6]], "l.es": [[1, 9, 8]], "le.s": [[1, 9, 8], [1, 9, 8]], "les.": [[1, 9, 8]], "less": [[1, 9, 8]], "l.ss": [[1, 9, 8]], "lss": [[1, 9, 6]], "l.ess": [[1, 9, 10]], "le.ss": [[1, 9, 10]], "les.s": [[1, 9, 10]], "less.": [[1, 9, 10]], "less ": [[1, 9, 10]], "l.ss ": [[1, 9, 10]], "lss ": [[1, 9, 8]], "l.ess ": [[1, 9, 12]], "le.s ": [[1, 9, 10]], "les ": [[1, 9, 8], [1, 9, 8]], "le.ss ": [[1, 9, 12]], "les. ": [[1, 9, 10]], "les.s ": [[1, 9, 12]], "less. ": [[1, 9, 12]], "less .": [[1, 9, 12]], "less p": [[1, 9, 12]], "l.ss p": [[1, 9, 12]], "lss p": [[1, 9, 10]], "l.ess p": [[1, 9, 14]], "le.s p": [[1, 9, 12]], "les p": [[1, 9, 10], [1, 9, 10]], "le.ss p": [[1, 9, 14]], "les. p": [[1, 9, 12]], "les.s p": [[1, 9, 14]], "less.p": [[1, 9, 12]], "lessp": [[1, 9, 10]], "less. p": [[1, 9, 14]], "less .p": [[1, 9, 14]], "less p.": [[1, 9, 14]], "less pe": [[1, 9, 14]], "l.ss pe": [[1, 9, 14]], "lss pe": [[1, 9, 12]], "l.ess pe": [[1, 9, 16]], "le.s pe": [[1, 9, 14]], "les pe": [[1, 9, 12], [1, 9, 12]], "le.ss pe": [[1, 9, 16]], "les. pe": [[1, 9, 14]], "les.s pe": [[1, 9, 16]], "less.pe": [[1, 9, 14]], "lesspe": [[1, 9, 12]], "less. pe": [[1, 9, 16]], "less .e": [[1, 9, 14]], "less e": [[1, 9, 12]], "less .pe": [[1, 9, 16]], "less p.e": [[1, 9, 16]], "less pe.": [[1, 9, 16]], "less peo": [[1, 9, 16]], "l.ss peo": [[1, 9, 16]], "lss peo": [[1, 9, 14]], "l.ess peo": [[1, 9, 18]], "le.s peo": [[1, 9, 16]], "les peo": [[1, 9, 14], [1, 9, 14]], "le.ss peo": [[1, 9, 18]], "les. peo": [[1, 9, 16]], "les.s peo": [[1, 9, 18]], "less.peo": [[1, 9, 16]], "lesspeo": [[1, 9, 14]], "less. peo": [[1, 9, 18]], "less .eo": [[1, 9, 16]], "less eo": [[1, 9, 14]], "less .peo": [[1, 9, 18]], "less p.o": [[1, 9, 16]], "less po": [[1, 9, 14]], "less p.eo": [[1, 9, 18]], "less pe.o": [[1, 9, 18]], "less peo.": [[1, 9, 18]], "less peop": [[1, 9, 18]], "l.ss peop": [[1, 9, 18]], "lss peop": [[1, 9, 16]], "l.ess peop": [[1, 9, 20]], "le.s peop": [[1, 9, 18]], "les peop": [[1, 9, 16], [1, 9, 16]], "le.ss peop": [[1, 9, 20]], "les. peop": [[1, 9, 18]], "les.s peop": [[1, 9, 20]], "less.peop": [[1, 9, 18]], "lesspeop": [[1, 9, 16]], "less. peop": [[1, 9, 20]], "less .eop": [[1, 9, 18]], "less eop": [[1, 9, 16]], "less .peop": [[1, 9, 20]], "less p.op": [[1, 9, 18]], "less pop": [[1, 9, 16]], "less p.eop": [[1, 9, 20]], "less pe.p": [[1, 9, 18]], "less pep": [[1, 9, 16]], "less pe.op": [[1, 9, 20]], "less peo.p": [[1, 9, 20]], "less peop.": [[1, 9, 20]], "lea": [[1, 10, 6], [1, 50, 6]], "l.ea": [[1, 10, 8], [1, 50, 8]], "le.a": [[1, 10, 8], [1, 50, 8]], "lea.": [[1, 10, 8], [1, 50, 8]], "lear": [[1, 10, 8], [1, 50, 8]], "l.ar": [[1, 10, 8], [1, 50, 8]], "lar": [[1, 10, 6], [1, 50, 6]], "l.ear": [[1, 10, 10], [1, 50, 10]], "le.r": [[1, 10, 8], [1, 50, 8]], "ler": [[1, 10, 6], [1, 50, 6]], "le.ar": [[1, 10, 10], [1, 50, 10]], "lea.r": [[1, 10, 10], [1, 50, 10]], "lear.": [[1, 10, 10], [1, 50, 10]], "learn": [[1, 10, 10], [1, 50, 10]], "l.arn": [[1, 10, 10], [1, 50, 10]], "larn": [[1, 10, 8], [1, 50, 8]], "l.earn": [[1, 10, 12], [1, 50, 12]], "le.rn": [[1, 10, 10], [1, 50, 10]], "lern": [[1, 10, 8], [1, 50, 8]], "le.arn": [[1, 10, 12], [1, 50, 12]], "lea.n": [[1, 10, 10], [1, 50, 10]], "lean": [[1, 10, 8], [1, 50, 8]], "lea.rn": [[1, 10, 12], [1, 50, 12]], "lear.n": [[1, 10, 12], [1, 50, 12]], "learn.": [[1, 10, 12], [1, 50, 12]], "learn ": [[1, 10, 12], [1, 50, 12]], "l.arn ": [[1, 10, 12], [1, 50, 12]], "larn ": [[1, 10, 10], [1, 50, 10]], "l.earn ": [[1, 10, 14], [1, 50, 14]], "le.rn ": [[1, 10, 12], [1, 50, 12]], "lern ": [[1, 10, 10], [1, 50, 10]], "le.arn ": [[1, 10, 14], [1, 50, 14]], "lea.n ": [[1, 10, 12], [1, 50, 12]], "lean ": [[1, 10, 10], [1, 50, 10]], "lea.rn ": [[1, 10, 14], [1, 50, 14]], "lear. ": [[1, 10, 12], [1, 50, 12]], "lear ": [[1, 10, 10], [1, 50, 10]], "lear.n ": [[1, 10, 14], [1, 50, 14]], "learn. ": [[1, 10, 14], [1, 50, 14]], "learn .": [[1, 10, 14], [1, 50, 14]], "learn h": [[1, 10, 14], [1, 50, 14]], "l.arn h": [[1, 10, 14]], "larn h": [[1, 10, 12]], "l.earn h": [[1, 10, 16]], "le.rn h": [[1, 10, 14]], "lern h": [[1, 10, 12]], "le.arn h": [[1, 10, 16]], "lea.n h": [[1, 10, 14]], "lean h": [[1, 10, 12]], "lea.rn h": [[1, 10, 16]], "lear. h": [[1, 10, 14]], "lear h": [[1, 10, 12]], "lear.n h": [[1, 10, 16]], "learn.h": [[1, 10, 14]], "learnh": [[1, 10, 12]], "learn. h": [[1, 10, 16]], "learn .h": [[1, 10, 16], [1, 50, 16]], "learn h.": [[1, 10, 16]], "learn ho": [[1, 10, 16]], "l.arn ho": [[1, 10, 16]], "larn ho": [[1, 10, 14]], "l.earn ho": [[1, 10, 18]], "le.rn ho": [[1, 10, 16]], "lern ho": [[1, 10, 14]], "le.arn ho": [[1, 10, 18]], "lea.n ho": [[1, 10, 16]], "lean ho": [[1, 10, 14]], "lea.rn ho": [[1, 10, 18]], "lear. ho": [[1, 10, 16]], "lear ho": [[1, 10, 14]], "lear.n ho": [[1, 10, 18]], "learn.ho": [[1, 10, 16]], "learnho": [[1, 10, 14]], "learn. ho": [[1, 10, 18]], "learn .o": [[1, 10, 16]], "learn o": [[1, 10, 14]], "learn .ho": [[1, 10, 18]], "learn h.o": [[1, 10, 18]], "learn ho.": [[1, 10, 18]], "learn how": [[1, 10, 18]], "l.arn how": [[1, 10, 18]], "larn how": [[1, 10, 16]], "l.earn how": [[1, 10, 20]], "le.rn how": [[1, 10, 18]], "lern how": [[1, 10, 16]], "le.arn how": [[1, 10, 20]], "lea.n how": [[1, 10, 18]], "lean how": [[1, 10, 16]], "lea.rn how": [[1, 10, 20]], "lear. how": [[1, 10, 18]], "lear how": [[1, 10, 16]], "lear.n how": [[1, 10, 20]], "learn.how": [[1, 10, 18]], "learnhow": [[1, 10, 16]], "learn. how": [[1, 10, 20]], "learn .ow": [[1, 10, 18]], "learn ow": [[1, 10, 16]], "learn .how": [[1, 10, 20]], "learn h.w": [[1, 10, 18]], "learn hw": [[1, 10, 16]], "learn h.ow": [[1, 10, 20]], "learn ho.w": [[1, 10, 20]], "learn how.": [[1, 10, 20]], "like to p": [[1, 16, 18]], "l.ke to p": [[1, 16, 18]], "lke to p": [[1, 16, 16]], "l.ike to p": [[1, 16, 20]], "li.e to p": [[1, 16, 18]], "lie to p": [[1, 16, 16]], "li.ke to p": [[1, 16, 20]], "lik. to p": [[1, 16, 18]], "lik to p": [[1, 16, 16]], "lik.e to p": [[1, 16, 20]], "like.to p": [[1, 16, 18]], "liketo p": [[1, 16, 16]], "like. to p": [[1, 16, 20]], "like .o p": [[1, 16, 18]], "like o p": [[1, 16, 16]], "like .to p": [[1, 16, 20]], "like t. p": [[1, 16, 18]], "like t p": [[1, 16, 16]], "like t.o p": [[1, 16, 20]], "like to.p": [[1, 16, 18]], "like top": [[1, 16, 16]], "like to. p": [[1, 16, 20]], "like to .p": [[1, 16, 20]], "like to p.": [[1, 16, 20]], "listp": [[1, 22, 10]], "l.stp": [[1, 22, 10]], "lstp": [[1, 22, 8]], "l.istp": [[1, 22, 12]], "li.tp": [[1, 22, 10]], "litp": [[1, 22, 8]], "li.stp": [[1, 22, 12]], "lis.p": [[1, 22, 10]], "lisp": [[1, 22, 8]], "lis.tp": [[1, 22, 12]], "list.p": [[1, 22, 12]], "listp.": [[1, 22, 12]], "listpy": [[1, 22, 12]], "l.stpy": [[1, 22, 12]], "lstpy": [[1, 22, 10]], "l.istpy": [[1, 22, 14]], "li.tpy": [[1, 22, 12]], "litpy": [[1, 22, 10]], "li.stpy": [[1, 22, 14]], "lis.py": [[1, 22, 12]], "lispy": [[1, 22, 10]], "lis.tpy": [[1, 22, 14]], "list.y": [[1, 22, 12]], "listy": [[1, 22, 10]], "list.py": [[1, 22, 14]], "listp.y": [[1, 22, 14]], "listpy.": [[1, 22, 14]], "listpyt": [[1, 22, 14]], "l.stpyt": [[1, 22, 14]], "lstpyt": [[1, 22, 12]], "l.istpyt": [[1, 22, 16]], "li.tpyt": [[1, 22, 14]], "litpyt": [[1, 22, 12]], "li.stpyt": [[1, 22, 16]], "lis.pyt": [[1, 22, 14]], "lispyt": [[1, 22, 12]], "lis.tpyt": [[1, 22, 16]], "list.yt": [[1, 22, 14]], "listyt": [[1, 22, 12]], "list.pyt": [[1, 22, 16]], "listp.t": [[1, 22, 14]], "listpt": [[1, 22, 12]], "listp.yt": [[1, 22, 16]], "listpy.t": [[1, 22, 16]], "listpyt.": [[1, 22, 16]], "listpyth": [[1, 22, 16]], "l.stpyth": [[1, 22, 16]], "lstpyth": [[1, 22, 14]], "l.istpyth": [[1, 22, 18]], "li.tpyth": [[1, 22, 16]], "litpyth": [[1, 22, 14]], "li.stpyth": [[1, 22, 18]], "lis.pyth": [[1, 22, 16]], "lispyth": [[1, 22, 14]], "lis.tpyth": [[1, 22, 18]], "list.yth": [[1, 22, 16]], "listyth": [[1, 22, 14]], "list.pyth": [[1, 22, 18]], "listp.th": [[1, 22, 16]], "listpth": [[1, 22, 14]], "listp.yth": [[1, 22, 18]], "listpy.h": [[1, 22, 16]], "listpyh": [[1, 22, 14]], "listpy.th": [[1, 22, 18]], "listpyt.h": [[1, 22, 18]], "listpyth.": [[1, 22, 18]], "listpytho": [[1, 22, 18]], "l.stpytho": [[1, 22, 18]], "lstpytho": [[1, 22, 16]], "l.istpytho": [[1, 22, 20]], "li.tpytho": [[1, 22, 18]], "litpytho": [[1, 22, 16]], "li.stpytho": [[1, 22, 20]], "lis.pytho": [[1, 22, 18]], "lispytho": [[1, 22, 16]], "lis.tpytho": [[1, 22, 20]], "list.ytho": [[1, 22, 18]], "listytho": [[1, 22, 16]], "list.pytho": [[1, 22, 20]], "listp.tho": [[1, 22, 18]], "listptho": [[1, 22, 16]], "listp.ytho": [[1, 22, 20]], "listpy.ho": [[1, 22, 18]], "listpyho": [[1, 22, 16]], "listpy.tho": [[1, 22, 20]], "listpyt.o": [[1, 22, 18]], "listpyto": [[1, 22, 16]], "listpyt.ho": [[1, 22, 20]], "listpyth.o": [[1, 22, 20]], "listpytho.": [[1, 22, 20]], "list r": [[1, 22, 12]], "l.st r": [[1, 22, 12]], "lst r": [[1, 22, 10]], "l.ist r": [[1, 22, 14]], "li.t r": [[1, 22, 12]], "lit r": [[1, 22, 10]], "li.st r": [[1, 22, 14]], "lis. r": [[1, 22, 12]], "lis r": [[1, 22, 10]], "lis.t r": [[1, 22, 14]], "list.r": [[1, 22, 12]], "listr": [[1, 22, 10]], "list. r": [[1, 22, 14]], "list .r": [[1, 22, 14]], "list r.": [[1, 22, 14]], "list ru": [[1, 22, 14]], "l.st ru": [[1, 22, 14]], "lst ru": [[1, 22, 12]], "l.ist ru": [[1, 22, 16]], "li.t ru": [[1, 22, 14]], "lit ru": [[1, 22, 12]], "li.st ru": [[1, 22, 16]], "lis. ru": [[1, 22, 14]], "lis ru": [[1, 22, 12]], "lis.t ru": [[1, 22, 16]], "list.ru": [[1, 22, 14]], "listru": [[1, 22, 12]], "list. ru": [[1, 22, 16]], "list .u": [[1, 22, 14]], "list u": [[1, 22, 12]], "list .ru": [[1, 22, 16]], "list r.u": [[1, 22, 16]], "list ru.": [[1, 22, 16]], "list run": [[1, 22, 16]], "l.st run": [[1, 22, 16]], "lst run": [[1, 22, 14]], "l.ist run": [[1, 22, 18]], "li.t run": [[1, 22, 16]], "lit run": [[1, 22, 14]], "li.st run": [[1, 22, 18]], "lis. run": [[1, 22, 16]], "lis run": [[1, 22, 14]], "lis.t run": [[1, 22, 18]], "list.run": [[1, 22, 16]], "listrun": [[1, 22, 14]], "list. run": [[1, 22, 18]], "list .un": [[1, 22, 16]], "list un": [[1, 22, 14]], "list .run": [[1, 22, 18]], "list r.n": [[1, 22, 16]], "list rn": [[1, 22, 14]], "list r.un": [[1, 22, 18]], "list ru.n": [[1, 22, 18]], "list run.": [[1, 22, 18]], "list run ": [[1, 22, 18]], "l.st run ": [[1, 22, 18]], "lst run ": [[1, 22, 16]], "l.ist run ": [[1, 22, 20]], "li.t run ": [[1, 22, 18]], "lit run ": [[1, 22, 16]], "li.st run ": [[1, 22, 20]], "lis. run ": [[1, 22, 18]], "lis run ": [[1, 22, 16]], "lis.t run ": [[1, 22, 20]], "list.run ": [[1, 22, 18]], "listrun ": [[1, 22, 16]], "list. run ": [[1, 22, 20]], "list .un ": [[1, 22, 18]], "list un ": [[1, 22, 16]], "list .run ": [[1, 22, 20]], "list r.n ": [[1, 22, 18]], "list rn ": [[1, 22, 16]], "list r.un ": [[1, 22, 20]], "list ru. ": [[1, 22, 18]], "list ru ": [[1, 22, 16]], "list ru.n ": [[1, 22, 20]], "list run. ": [[1, 22, 20]], "list run .": [[1, 22, 20]], "list of d": [[1, 28, 18]], "l.st of d": [[1, 28, 18]], "lst of d": [[1, 28, 16]], "l.ist of d": [[1, 28, 20]], "li.t of d": [[1, 28, 18]], "lit of d": [[1, 28, 16]], "li.st of d": [[1, 28, 20]], "lis. of d": [[1, 28, 18]], "lis of d": [[1, 28, 16]], "lis.t of d": [[1, 28, 20]], "list.of d": [[1, 28, 18]], "listof d": [[1, 28, 16]], "list. of d": [[1, 28, 20]], "list .f d": [[1, 28, 18]], "list f d": [[1, 28, 16]], "list .of d": [[1, 28, 20]], "list o. d": [[1, 28, 18]], "list o d": [[1, 28, 16]], "list o.f d": [[1, 28, 20]], "list of.d": [[1, 28, 18]], "list ofd": [[1, 28, 16]], "list of. d": [[1, 28, 20]], "list of .d": [[1, 28, 20]], "list of d.": [[1, 28, 20]], "learn w": [[1, 50, 14]], "l.arn w": [[1, 50, 14]], "larn w": [[1, 50, 12]], "l.earn w": [[1, 50, 16]], "le.rn w": [[1, 50, 14]], "lern w": [[1, 50, 12]], "le.arn w": [[1, 50, 16]], "lea.n w": [[1, 50, 14]], "lean w": [[1, 50, 12]], "lea.rn w": [[1, 50, 16]], "lear. w": [[1, 50, 14]], "lear w": [[1, 50, 12]], "lear.n w": [[1, 50, 16]], "learn.w": [[1, 50, 14]], "learnw": [[1, 50, 12]], "learn. w": [[1, 50, 16]], "learn .w": [[1, 50, 16]], "learn w.": [[1, 50, 16]], "learn wh": [[1, 50, 16]], "l.arn wh": [[1, 50, 16]], "larn wh": [[1, 50, 14]], "l.earn wh": [[1, 50, 18]], "le.rn wh": [[1, 50, 16]], "lern wh": [[1, 50, 14]], "le.arn wh": [[1, 50, 18]], "lea.n wh": [[1, 50, 16]], "lean wh": [[1, 50, 14]], "lea.rn wh": [[1, 50, 18]], "lear. wh": [[1, 50, 16]], "lear wh": [[1, 50, 14]], "lear.n wh": [[1, 50, 18]], "learn.wh": [[1, 50, 16]], "learnwh": [[1, 50, 14]], "learn. wh": [[1, 50, 18]], "learn .wh": [[1, 50, 18]], "learn w.h": [[1, 50, 18]], "learn wh.": [[1, 50, 18]], "learn wha": [[1, 50, 18]], "l.arn wha": [[1, 50, 18]], "larn wha": [[1, 50, 16]], "l.earn wha": [[1, 50, 20]], "le.rn wha": [[1, 50, 18]], "lern wha": [[1, 50, 16]], "le.arn wha": [[1, 50, 20]], "lea.n wha": [[1, 50, 18]], "lean wha": [[1, 50, 16]], "lea.rn wha": [[1, 50, 20]], "lear. wha": [[1, 50, 18]], "lear wha": [[1, 50, 16]], "lear.n wha": [[1, 50, 20]], "learn.wha": [[1, 50, 18]], "learnwha": [[1, 50, 16]], "learn. wha": [[1, 50, 20]], "learn .ha": [[1, 50, 18]], "learn ha": [[1, 50, 16]], "learn .wha": [[1, 50, 20]], "learn w.a": [[1, 50, 18]], "learn wa": [[1, 50, 16]], "learn w.ha": [[1, 50, 20]], "learn wh.a": [[1, 50, 20]], "learn wha.": [[1, 50, 20]]}]